leolib/__init__.py
leolib/api.py
leolib/helper.py
leolib-1.1.0.dist-info/LICENSE
leolib-1.1.0.dist-info/METADATA
leolib-1.1.0.dist-info/WHEEL
leolib-1.1.0.dist-info/top_level.txt
leolib-1.1.0.dist-info/RECORD
