Metadata-Version: 2.1
Name: leolib
Version: 1.1.0
Summary: 利昂图书馆api打包
Home-page: UNKNOWN
Author: AntonVanke
Author-email: fjs0801@gmail.com
License: UNKNOWN
Platform: UNKNOWN
Classifier: Programming Language :: Python :: 3
Classifier: License :: OSI Approved :: MIT License
Classifier: Operating System :: OS Independent
Requires-Python: >=3
Requires-Dist: requests
